README.md
bflower/__main__.py
bflower/alembic/README
bflower/alembic/env.py
bflower/alembic/script.py.mako
bflower/alembic/versions/006b3990db50_add_unique_constraints.py
bflower/alembic/versions/0b8757876a7c_.py
bflower/alembic/versions/1a110b568907_replace_credential_table_with_variable.py
bflower/alembic/versions/1ef9c4f3765d_.py
bflower/alembic/versions/1f4d6df60295_add_default_fields_column.py
bflower/alembic/versions/260dbcc8b680_adds_tables.py
bflower/alembic/versions/2ac71eb9c3ae_adds_credential_table.py
bflower/alembic/versions/4e5980a44eaa_fix_date_times_again.py
bflower/alembic/versions/58b28437a398_modify_nullable.py
bflower/alembic/versions/63b9c451fd30_add_icon_and_icon_bg_color_to_flow.py
bflower/alembic/versions/67cc006d50bf_add_profile_image_column.py
bflower/alembic/versions/6e7b581b5648_fix_nullable.py
bflower/alembic/versions/7843803a87b5_store_updates.py
bflower/alembic/versions/79e675cb6752_change_datetime_type.py
bflower/alembic/versions/7d2162acc8b2_adds_updated_at_and_folder_cols.py
bflower/alembic/versions/b2fa308044b5_add_unique_constraints.py
bflower/alembic/versions/bc2f01c40e4a_new_fixes.py
bflower/alembic/versions/c153816fd85f_set_name_and_value_to_not_nullable.py
bflower/alembic/versions/e3bc869fa272_fix_nullable.py
bflower/alembic/versions/eb5866d51fd2_change_columns_to_be_nullable.py
bflower/alembic/versions/f5ee9749d1a6_user_id_can_be_null_in_flow.py
bflower/alembic/versions/fd531f8868b1_fix_credential_table.py
bflower/alembic.ini
bflower/api/__init__.py
bflower/api/router.py
bflower/api/utils.py
bflower/api/v1/__init__.py
bflower/api/v1/api_key.py
bflower/api/v1/base.py
bflower/api/v1/callback.py
bflower/api/v1/chat.py
bflower/api/v1/endpoints.py
bflower/api/v1/files.py
bflower/api/v1/flows.py
bflower/api/v1/login.py
bflower/api/v1/monitor.py
bflower/api/v1/schemas.py
bflower/api/v1/store.py
bflower/api/v1/users.py
bflower/api/v1/validate.py
bflower/api/v1/variable.py
bflower/base/__init__.py
bflower/base/agents/__init__.py
bflower_base-0.0.43.dist-info/METADATA
bflower_base-0.0.43.dist-info/WHEEL
bflower_base-0.0.43.dist-info/entry_points.txt
bflower_base-0.0.43.dist-info/RECORD
